{
  "/_not-found/page": "app/_not-found/page.js",
  "/api/auth/login/route": "app/api/auth/login/route.js",
  "/api/auth/logout/route": "app/api/auth/logout/route.js",
  "/api/auth/reset-password/route": "app/api/auth/reset-password/route.js",
  "/api/auth/session/route": "app/api/auth/session/route.js",
  "/api/content-blocks/route": "app/api/content-blocks/route.js",
  "/api/content-interactions/route": "app/api/content-interactions/route.js",
  "/api/course-sections/route": "app/api/course-sections/route.js",
  "/api/courses/[slug]/sections/[sectionId]/content/route": "app/api/courses/[slug]/sections/[sectionId]/content/route.js",
  "/api/courses/[slug]/sections/route": "app/api/courses/[slug]/sections/route.js",
  "/api/courses/route": "app/api/courses/route.js",
  "/api/enrollments/route": "app/api/enrollments/route.js",
  "/api/plants/route": "app/api/plants/route.js",
  "/api/progress/route": "app/api/progress/route.js",
  "/api/public/content-blocks/route": "app/api/public/content-blocks/route.js",
  "/api/public/course-sections/route": "app/api/public/course-sections/route.js",
  "/api/public/courses/route": "app/api/public/courses/route.js",
  "/api/public/quiz-questions/route": "app/api/public/quiz-questions/route.js",
  "/api/quiz-analytics/route": "app/api/quiz-analytics/route.js",
  "/api/quiz-attempts/route": "app/api/quiz-attempts/route.js",
  "/api/quiz-questions/route": "app/api/quiz-questions/route.js",
  "/api/reports/route": "app/api/reports/route.js",
  "/api/stats/dashboard/route": "app/api/stats/dashboard/route.js",
  "/api/stats/site/route": "app/api/stats/site/route.js",
  "/api/translations/[courseId]/route": "app/api/translations/[courseId]/route.js",
  "/api/translations/section/[sectionId]/route": "app/api/translations/section/[sectionId]/route.js",
  "/api/user-progress/route": "app/api/user-progress/route.js",
  "/auth/login/page": "app/auth/login/page.js",
  "/auth/register/page": "app/auth/register/page.js",
  "/courses/[slug]/complete/page": "app/courses/[slug]/complete/page.js",
  "/courses/[slug]/learn/[sectionId]/page": "app/courses/[slug]/learn/[sectionId]/page.js",
  "/courses/[slug]/learn/page": "app/courses/[slug]/learn/page.js",
  "/courses/[slug]/page": "app/courses/[slug]/page.js",
  "/courses/page": "app/courses/page.js",
  "/dashboard/page": "app/dashboard/page.js",
  "/enrollments/page": "app/enrollments/page.js",
  "/favicon.ico/route": "app/favicon.ico/route.js",
  "/page": "app/page.js",
  "/plants/page": "app/plants/page.js",
  "/progress/page": "app/progress/page.js",
  "/reports/page": "app/reports/page.js",
  "/settings/page": "app/settings/page.js",
  "/users/page": "app/users/page.js"
}